setup.cfg
setup.py
spark_notebook_helpers3/__init__.py
spark_notebook_helpers3.egg-info/PKG-INFO
spark_notebook_helpers3.egg-info/SOURCES.txt
spark_notebook_helpers3.egg-info/dependency_links.txt
spark_notebook_helpers3.egg-info/requires.txt
spark_notebook_helpers3.egg-info/top_level.txt